mkdocs_mcp/__init__.py
mkdocs_mcp/__main__.py
mkdocs_mcp/plugin.py
mkdocs_mcp/py.typed
mkdocs_mcp-0.1.3.dist-info/METADATA
mkdocs_mcp-0.1.3.dist-info/WHEEL
mkdocs_mcp-0.1.3.dist-info/entry_points.txt
mkdocs_mcp-0.1.3.dist-info/licenses/LICENSE
mkdocs_mcp-0.1.3.dist-info/RECORD
