Metadata-Version: 2.4
Name: mkdocs-mcp
Version: 0.1.3
Summary: Add your description here
Author-email: Urs Baumann <github@m.ubaumann.ch>
License-File: LICENSE
Requires-Python: >=3.12
Requires-Dist: html2text>=2025.4.15
Requires-Dist: mcp[cli]>=1.6.0
Requires-Dist: mkdocs>=1.6.1
Requires-Dist: rich>=14.0.0
